pyairbnb/__init__.py
pyairbnb/api.py
pyairbnb/calendarinfo.py
pyairbnb/details.py
pyairbnb/experience.py
pyairbnb/host.py
pyairbnb/host_details.py
pyairbnb/parse.py
pyairbnb/price.py
pyairbnb/reviews.py
pyairbnb/search.py
pyairbnb/standardize.py
pyairbnb/start.py
pyairbnb/utils.py
pyairbnb-2.2.0.dist-info/licenses/LICENSE
pyairbnb-2.2.0.dist-info/METADATA
pyairbnb-2.2.0.dist-info/WHEEL
pyairbnb-2.2.0.dist-info/top_level.txt
pyairbnb-2.2.0.dist-info/RECORD
