Metadata-Version: 2.4
Name: pyairbnb
Version: 2.2.0
Summary: Airbnb scraper in Python
Author-email: John Balvin <johnchristian@hotmail.es>
Project-URL: Homepage, https://github.com/johnbalvin/pyairbnb
Keywords: airbnb,scraper,crawler,bot,reviews
License-File: LICENSE
Requires-Dist: curl_cffi
Requires-Dist: bs4
Requires-Dist: requests
Dynamic: license-file
